BuildVuClient/BuildVu.py
BuildVuClient/__init__.py
buildvu-4.1.5.dist-info/LICENSE.txt
buildvu-4.1.5.dist-info/METADATA
buildvu-4.1.5.dist-info/WHEEL
buildvu-4.1.5.dist-info/top_level.txt
buildvu-4.1.5.dist-info/RECORD
