Metadata-Version: 2.1
Name: buildvu
Version: 4.1.5
Summary: [Deprecated] Future development has been directed to IDRCloudClient, which can be used for the same purpose.
Home-page: https://github.com/idrsolutions/buildvu-python-client
Author: IDRSolutions
Author-email: support@idrsolutions.zendesk.com
License: Apache 2.0
Project-URL: Source, https://github.com/idrsolutions/buildvu-python-client/
Project-URL: Tracker, https://github.com/idrsolutions/buildvu-python-client/issues
Project-URL: Contact us, https://idrsolutions.zendesk.com/hc/en-us/requests/new
Keywords: idrsolutions pdf html5 converter buildvu microservice example web application server API python client deprecated
Platform: UNKNOWN
Classifier: Development Status :: 7 - Inactive
Classifier: Intended Audience :: Developers
Classifier: Topic :: Software Development :: Libraries :: Python Modules
Classifier: License :: OSI Approved :: Apache Software License
Classifier: Programming Language :: Python :: 3 :: Only
Requires-Dist: requests
